jvclient/__init__.py
jvclient/lib/__init__.py
jvclient/lib/utils.py
jvclient/lib/widgets.py
jvclient-2.1.25.dist-info/licenses/LICENSE
jvclient-2.1.25.dist-info/METADATA
jvclient-2.1.25.dist-info/WHEEL
jvclient-2.1.25.dist-info/top_level.txt
jvclient-2.1.25.dist-info/RECORD
