Metadata-Version: 2.4
Name: jvclient
Version: 2.1.25
Summary: JIVAS client library for action development.
Home-page: https://github.com/TrueSelph/jvclient
Author: TrueSelph Inc.
Author-email: admin@trueselph.com
Keywords: jivas
Requires-Python: >=3.12.0
License-File: LICENSE
Requires-Dist: pyaml>=25.1.0
Requires-Dist: requests>=2.32.3
Provides-Extra: dev
Requires-Dist: pre-commit; extra == "dev"
Requires-Dist: pytest; extra == "dev"
Requires-Dist: pytest-mock; extra == "dev"
Requires-Dist: pytest-cov; extra == "dev"
Requires-Dist: coverage; extra == "dev"
Dynamic: author
Dynamic: author-email
Dynamic: description
Dynamic: description-content-type
Dynamic: home-page
Dynamic: keywords
Dynamic: license-file
Dynamic: provides-extra
Dynamic: requires-dist
Dynamic: requires-python
Dynamic: summary
